django_email_password_reset-0.1.1.dist-info/DESCRIPTION.rst
django_email_password_reset-0.1.1.dist-info/METADATA
django_email_password_reset-0.1.1.dist-info/metadata.json
django_email_password_reset-0.1.1.dist-info/RECORD
django_email_password_reset-0.1.1.dist-info/top_level.txt
django_email_password_reset-0.1.1.dist-info/WHEEL
password_reset/__init__.py
password_reset/models.py
password_reset/management/__init__.py
password_reset/management/commands/__init__.py
password_reset/management/commands/reset_passwords.py
password_reset/templates/password_reset/email.txt
password_reset/templates/password_reset/email_subject.txt
