Metadata-Version: 2.0
Name: django-email-password-reset
Version: 0.1.1
Summary: Minimalist app disabling all passwords and sending password reset emails.
Home-page: https://github.com/dokterbob/django-email-password-reset/
Author: Mathijs de Bruin
Author-email: mathijs@mathijsfietst.nl
License: BSD
Platform: UNKNOWN
Classifier: Development Status :: 3 - Alpha
Classifier: Environment :: Web Environment
Classifier: Framework :: Django
Classifier: Intended Audience :: Developers
Classifier: License :: OSI Approved :: BSD License
Classifier: Operating System :: OS Independent
Classifier: Programming Language :: Python
Classifier: Topic :: Utilities
